TracerLL.cpython-314-x86_64-linux-gnu.so
TracerLL/SevenBitEncoding.cpython-314-x86_64-linux-gnu.so
TracerLL/Tracer.cpython-314-x86_64-linux-gnu.so
TracerLL/__init__.py
tracerll-0.2.7.dist-info/METADATA
tracerll-0.2.7.dist-info/WHEEL
tracerll-0.2.7.dist-info/top_level.txt
tracerll-0.2.7.dist-info/RECORD
tracerll-0.2.7.dist-info/licenses/LICENSE
