Metadata-Version: 2.4
Name: TracerLL
Version: 0.2.7
Summary: TracerLL: High-performance embedded variable tracing library
Author-email: Jos Wigchert <joswigchert@integralmotions.com>, William Kers <williamkers@integralmotions.com>
License: MIT
Requires-Python: >=3.9
License-File: LICENSE
Dynamic: license-file
